{
  "type": "FeatureCollection",
  "features": [
 
    {
      "type": "Feature",
      "properties": {
        "name": "Teraco JB1",
        "description": "PoP",
        "address": "5 Brewery St\nIsando\nKempton Park\n1600\nSouth Africa",
        "image": "https://uploads-ssl.webflow.com/6453980466edcb7b60b5acc6/64adbec1ed61980a7ccc881a_viettel.svg"
      },
      "geometry": {
        "type": "Point",
        "coordinates": [
          28.19772974503535, 
          -26.13774591087882
        ]
      
    }
  ]
}
