{
  "type": "FeatureCollection",
  "features": [
    {
      "type": "Feature",
      "properties": {
        "name": "NEXTDC P1",
        "description": "PoP",
        "address": "NEXTDC P1 
101 Malaga Dr/n>Malaga\nWA 6090
Australia",
        "image": "https://uploads-ssl.webflow.com/6453980466edcb7b60b5acc6/64adbec08873846c2c4b548d_nextdc.svg"
      },
      "geometry": {
        "type": "Point",
        "coordinates": [
          115.895902032381699,
          -31.864247023318459
        ]
      }
    },
    {
      "type": "Feature",
      "properties": {
        "name": "Equinix SY1",
        "description": "PoP",
        "address": "Equinix SY1<br>Unit B/C<br>639 Gardeners Road<br>Mascot<br>Sydney<br>NSW 2020<br>Australia",
        "image": "https://uploads-ssl.webflow.com/6453980466edcb7b60b5acc6/64adbec085da1d25d6824bc3_equinix.svg"
      },
      "geometry": {
        "type": "Point",
        "coordinates": [
          151.18819560213251,
          -33.921417095698907
        ]
      }
    }
  ]
}
