{
  "type": "FeatureCollection",
  "features": [
    {
      "type": "Feature",
      "properties": {
        "name": "SGGS NETWORK SDN. BHD.",
        "description": "Office",
        "address": "Office Address",
        "image": "https://uploads-ssl.webflow.com/6453980466edcb7b60b5acc6/645d24d0a232c66610f0851f_Logo%20(1).svg"
  
      },
      "geometry": {
        "type": "Point",
        "coordinates": [
          101.6789256, 
          2.9963089
        ]
      }
    },
    {
      "type": "Feature",
      "properties": {
        "name": "SG.GS (HK) LIMITED",
        "description": "Office",
        "address": "Office Address",
        "image": "https://uploads-ssl.webflow.com/6453980466edcb7b60b5acc6/645d24d0a232c66610f0851f_Logo%20(1).svg"
  
      },
      "geometry": {
        "type": "Point",
        "coordinates": [
          114.2061161, 
          22.32148650000001
        ]
      }
    },
    {
      "type": "Feature",
      "properties": {
        "name": "SG.GS INTERNATIONAL LTD",
        "description": "Office",
        "address": "Office Address",
        "image": "https://uploads-ssl.webflow.com/6453980466edcb7b60b5acc6/645d24d0a232c66610f0851f_Logo%20(1).svg"
  
      },
      "geometry": {
        "type": "Point",
        "coordinates": [
          -0.098546725422637, 
          51.51968165718548
        ]
      }
    },

    { "type": "Feature",
      "properties": {
        "name": "SG.GS PTE. LTD.",
        "description": "Office",
        "address": "Office Address",
        "image": "https://uploads-ssl.webflow.com/6453980466edcb7b60b5acc6/645d24d0a232c66610f0851f_Logo%20(1).svg"
  
      },
      "geometry": {
        "type": "Point",
        "coordinates": [
          103.920409099999901, 
          1.3233178
        ]   
      }
    }
  ]
}

