{
  "type": "FeatureCollection",
  "features": [
    {
      "type": "Feature",
      "properties": {
        "name": "SGGS NETWORK SDN. BHD.",
        "description": "Office",
        "address": "22-1, Jalan Equine 1D, Taman Equine, 43300, Seri Kembangan, Selangor, Malaysia",
        "image": "https://uploads-ssl.webflow.com/6453980466edcb7b60b5acc6/645d24d0a232c66610f0851f_Logo%20(1).svg"
  
      },
      "geometry": {
        "type": "Point",
        "coordinates": [
          101.6789256, 
          2.9963089
        ]
      }
    },
    {
      "type": "Feature",
      "properties": {
        "name": "SG.GS (HK) LIMITED",
        "description": "Office",
        "address": "10/F RM D, Tower A, Billion Centre, 1 Wang Kwong Road, Kowloon Bay, Kowloon, Hong Kong",
        "image": "https://uploads-ssl.webflow.com/6453980466edcb7b60b5acc6/645d24d0a232c66610f0851f_Logo%20(1).svg"
  
      },
      "geometry": {
        "type": "Point",
        "coordinates": [
          114.2061161, 
          22.32148650000001
        ]
      }
    },
    {
      "type": "Feature",
      "properties": {
        "name": "SG.GS INTERNATIONAL LTD",
        "description": "Office",
        "address": "80-83 Long Lane, London, EC1A 9ET United Kingdom",
        "image": "https://uploads-ssl.webflow.com/6453980466edcb7b60b5acc6/655636e7fb7c73d6c5e42e4a_sggs-logo-black.svg"
  
      },
      "geometry": {
        "type": "Point",
        "coordinates": [
          -0.098546725422637, 
          51.51968165718548
        ]
      }
    },

    { "type": "Feature",
      "properties": {
        "name": "SG.GS PTE. LTD.",
        "description": "Office",
        "address": "750C Chai Chee Road, #02-02, Viva Business Park, Singapore, 469003, Singapore",
        "image": "https://uploads-ssl.webflow.com/6453980466edcb7b60b5acc6/645d24d0a232c66610f0851f_Logo%20(1).svg"
  
      },
      "geometry": {
        "type": "Point",
        "coordinates": [
          103.920409099999901, 
          1.3233178
        ]   
      }
    }
  ]
}

